hype_python_boilerplate/__init__.py
hype_python_boilerplate/console.py
hype_python_boilerplate/wikipedia.py
hype_python_boilerplate-0.1.0.dist-info/entry_points.txt
hype_python_boilerplate-0.1.0.dist-info/LICENSE
hype_python_boilerplate-0.1.0.dist-info/WHEEL
hype_python_boilerplate-0.1.0.dist-info/METADATA
hype_python_boilerplate-0.1.0.dist-info/RECORD
