Metadata-Version: 2.1
Name: hype-python-boilerplate
Version: 0.1.0
Summary: hype-python-boilerplate, using example from cjolowicz.github.io
Home-page: https://github.com/ojefimow-test/hype-python-boilerplate
License: MIT
Keywords: hypermodern
Author: Alexei Efimov
Author-email: alexei.efimov@wirexapp.com
Requires-Python: >=3.8,<4.0
Classifier: License :: OSI Approved :: MIT License
Classifier: Programming Language :: Python :: 3
Classifier: Programming Language :: Python :: 3.8
Classifier: Programming Language :: Python :: 3.9
Requires-Dist: click (>=7.0,<8.0)
Requires-Dist: desert (>=2020.11.18,<2021.0.0)
Requires-Dist: marshmallow (>=3.11.1,<4.0.0)
Requires-Dist: requests (>=2.25.1,<3.0.0)
Project-URL: Repository, https://github.com/ojefimow-test/hype-python-boilerplate
